streamlit_supabase_auth/__init__.py
streamlit_supabase_auth/frontend/build/asset-manifest.json
streamlit_supabase_auth/frontend/build/index.html
streamlit_supabase_auth/frontend/build/static/css/main.8f115210.chunk.css
streamlit_supabase_auth/frontend/build/static/css/main.8f115210.chunk.css.map
streamlit_supabase_auth/frontend/build/static/js/2.63da4fb5.chunk.js
streamlit_supabase_auth/frontend/build/static/js/2.63da4fb5.chunk.js.LICENSE.txt
streamlit_supabase_auth/frontend/build/static/js/2.63da4fb5.chunk.js.map
streamlit_supabase_auth/frontend/build/static/js/main.c7bae7ac.chunk.js
streamlit_supabase_auth/frontend/build/static/js/main.c7bae7ac.chunk.js.map
streamlit_supabase_auth/frontend/build/static/js/runtime-main.4a39f77f.js
streamlit_supabase_auth/frontend/build/static/js/runtime-main.4a39f77f.js.map
streamlit_supabase_auth-1.0.2.dist-info/LICENSE
streamlit_supabase_auth-1.0.2.dist-info/METADATA
streamlit_supabase_auth-1.0.2.dist-info/WHEEL
streamlit_supabase_auth-1.0.2.dist-info/top_level.txt
streamlit_supabase_auth-1.0.2.dist-info/RECORD
