Metadata-Version: 2.1
Name: streamlit_supabase_auth
Version: 1.0.2
Summary: JWT authentication with Supabase
Home-page: https://github.com/sweatybridge/streamlit-supabase-auth
Author: Han Qiao
Author-email: sweatybridge@gmail.com
License: UNKNOWN
Platform: UNKNOWN
Classifier: Programming Language :: Python :: 3
Classifier: Programming Language :: Python :: 3.7
Classifier: Programming Language :: Python :: 3.8
Classifier: Programming Language :: Python :: 3.9
Classifier: Programming Language :: Python :: 3.10
Classifier: License :: OSI Approved :: Apache Software License
Classifier: Operating System :: OS Independent
Requires-Python: >=3.7
License-File: LICENSE
